MysqlHanshuDaquanCYuyanBianchengWangFix1/README.md
MysqlHanshuDaquanCYuyanBianchengWangFix1/__init__.py
MysqlHanshuDaquanCYuyanBianchengWangFix1/__main__.py
MysqlHanshuDaquanCYuyanBianchengWangFix1/file.epub
MysqlHanshuDaquanCYuyanBianchengWangFix1/index.html
MysqlHanshuDaquanCYuyanBianchengWangFix1/css/__init__.py
MysqlHanshuDaquanCYuyanBianchengWangFix1/css/annotations.css
MysqlHanshuDaquanCYuyanBianchengWangFix1/css/main.css
MysqlHanshuDaquanCYuyanBianchengWangFix1/css/normalize.css
MysqlHanshuDaquanCYuyanBianchengWangFix1/css/popup.css
MysqlHanshuDaquanCYuyanBianchengWangFix1/font/__init__.py
MysqlHanshuDaquanCYuyanBianchengWangFix1/font/fontello.eot
MysqlHanshuDaquanCYuyanBianchengWangFix1/font/fontello.svg
MysqlHanshuDaquanCYuyanBianchengWangFix1/font/fontello.ttf
MysqlHanshuDaquanCYuyanBianchengWangFix1/font/fontello.woff
MysqlHanshuDaquanCYuyanBianchengWangFix1/img/__init__.py
MysqlHanshuDaquanCYuyanBianchengWangFix1/img/annotator-glyph-sprite.png
MysqlHanshuDaquanCYuyanBianchengWangFix1/img/annotator-icon-sprite.png
MysqlHanshuDaquanCYuyanBianchengWangFix1/img/apple-touch-icon.png
MysqlHanshuDaquanCYuyanBianchengWangFix1/img/cancelfullscreen.png
MysqlHanshuDaquanCYuyanBianchengWangFix1/img/close.png
MysqlHanshuDaquanCYuyanBianchengWangFix1/img/fullscreen.png
MysqlHanshuDaquanCYuyanBianchengWangFix1/img/loader.gif
MysqlHanshuDaquanCYuyanBianchengWangFix1/img/menu-icon.png
MysqlHanshuDaquanCYuyanBianchengWangFix1/img/save.png
MysqlHanshuDaquanCYuyanBianchengWangFix1/img/saved.png
MysqlHanshuDaquanCYuyanBianchengWangFix1/img/settings-s.png
MysqlHanshuDaquanCYuyanBianchengWangFix1/img/settings.png
MysqlHanshuDaquanCYuyanBianchengWangFix1/img/star.png
MysqlHanshuDaquanCYuyanBianchengWangFix1/js/__init__.py
MysqlHanshuDaquanCYuyanBianchengWangFix1/js/epub.js
MysqlHanshuDaquanCYuyanBianchengWangFix1/js/epub.min.js
MysqlHanshuDaquanCYuyanBianchengWangFix1/js/epub.min.map
MysqlHanshuDaquanCYuyanBianchengWangFix1/js/hooks.min.js
mysql_hanshu_daquan_c_yuyan_biancheng_wang_fix1-2025.3.24.1.dist-info/METADATA
mysql_hanshu_daquan_c_yuyan_biancheng_wang_fix1-2025.3.24.1.dist-info/WHEEL
mysql_hanshu_daquan_c_yuyan_biancheng_wang_fix1-2025.3.24.1.dist-info/entry_points.txt
mysql_hanshu_daquan_c_yuyan_biancheng_wang_fix1-2025.3.24.1.dist-info/top_level.txt
mysql_hanshu_daquan_c_yuyan_biancheng_wang_fix1-2025.3.24.1.dist-info/RECORD
